lightblue_ai/__init__.py
lightblue_ai/agent.py
lightblue_ai/cli.py
lightblue_ai/log.py
lightblue_ai/mcps.py
lightblue_ai/settings.py
lightblue_ai/utils.py
lightblue_ai/models/__init__.py
lightblue_ai/models/doubao.py
lightblue_ai/prompts/__init__.py
lightblue_ai/prompts/templates/context.md
lightblue_ai/prompts/templates/system_prompt.md
lightblue_ai/tools/__init__.py
lightblue_ai/tools/base.py
lightblue_ai/tools/extensions.py
lightblue_ai/tools/manager.py
lightblue_ai/tools/media_mixin.py
lightblue_ai/tools/aigc/__init__.py
lightblue_ai/tools/aigc/flux_bfl.py
lightblue_ai/tools/document/__init__.py
lightblue_ai/tools/document/markitdown.py
lightblue_ai/tools/document/pdf.py
lightblue_ai/tools/enhance/__init__.py
lightblue_ai/tools/enhance/plan.py
lightblue_ai/tools/enhance/thinking.py
lightblue_ai/tools/local/__init__.py
lightblue_ai/tools/local/command.py
lightblue_ai/tools/local/files.py
lightblue_ai/tools/local/html_edit.py
lightblue_ai/tools/mas/__init__.py
lightblue_ai/tools/mas/dispatch_agent.py
lightblue_ai/tools/web/__init__.py
lightblue_ai/tools/web/crawler.py
lightblue_ai/tools/web/request.py
lightblue_ai/tools/web/save.py
lightblue_ai/tools/web/screenshot.py
lightblue_ai/tools/web/search_image.py
lightblue_ai/tools/web/webview.py
lightblue_ai-0.5.7.dist-info/METADATA
lightblue_ai-0.5.7.dist-info/WHEEL
lightblue_ai-0.5.7.dist-info/entry_points.txt
lightblue_ai-0.5.7.dist-info/licenses/LICENSE
lightblue_ai-0.5.7.dist-info/RECORD
