Metadata-Version: 2.4
Name: lightblue-ai
Version: 0.5.7
Summary: Light Blue is an agentic agent framework for building AI applications
Project-URL: Repository, https://github.com/ai-zerolab/lightblue-ai
Author-email: Wh1isper <jizhongsheng957@gmail.com>
License-File: LICENSE
Keywords: agent,agentic,llm
Classifier: Intended Audience :: Developers
Classifier: Programming Language :: Python
Classifier: Programming Language :: Python :: 3
Classifier: Programming Language :: Python :: 3.10
Classifier: Programming Language :: Python :: 3.11
Classifier: Programming Language :: Python :: 3.12
Classifier: Programming Language :: Python :: 3.13
Classifier: Topic :: Software Development :: Libraries :: Python Modules
Requires-Python: <4.0,>=3.10
Requires-Dist: httpx>=0.28.1
Requires-Dist: jinja2>=3.1.6
Requires-Dist: loguru>=0.7.3
Requires-Dist: lxml>=5.3.2
Requires-Dist: markitdown[all]>=0.1.1
Requires-Dist: mcp>=1.6.0
Requires-Dist: openai>=1.74.0
Requires-Dist: pdf2image>=1.17.0
Requires-Dist: pillow!=11.2.0,>=11.1.0
Requires-Dist: playwright>=1.51.0
Requires-Dist: pluggy>=1.5.0
Requires-Dist: pydantic-ai>=0.2.0
Requires-Dist: pydantic-settings>=2.8.1
Requires-Dist: pydantic>=2.11.1
Requires-Dist: pymupdf4llm>=0.0.21
Requires-Dist: python-dotenv>=1.1.0
Requires-Dist: rich>=14.0.0
Requires-Dist: tavily-python>=0.5.3
Requires-Dist: typer>=0.15.2
Requires-Dist: typing-extensions>=4.13.0
